fct/anoni.py
fct/csv2bib.py
fct/eml2csv.py
fct/eml2tex.py
fct/pdf2tex.py
fct/pdftxt2tex.py
fct/quotesearch.py
fct/timeline_plotter.py
fct1-0.0.1.dist-info/LICENSE
fct1-0.0.1.dist-info/METADATA
fct1-0.0.1.dist-info/WHEEL
fct1-0.0.1.dist-info/entry_points.txt
fct1-0.0.1.dist-info/RECORD
