Metadata-Version: 2.1
Name: fct1
Version: 0.0.1
Summary: command line utilities for preparation of quote databases from original documents, for use in family court
License: MIT
Author: tilmaerts
Author-email: 95282593+tilmaerts@users.noreply.github.com
Requires-Python: >=3.9,<4.0
Classifier: License :: OSI Approved :: MIT License
Classifier: Programming Language :: Python :: 3
Classifier: Programming Language :: Python :: 3.9
Classifier: Programming Language :: Python :: 3.10
Classifier: Programming Language :: Python :: 3.11
Classifier: Programming Language :: Python :: 3.12
Requires-Dist: bibtexparser (>=1.4.1,<2.0.0)
Requires-Dist: demoji (>=1.1.0,<2.0.0)
Requires-Dist: filelock (>=3.13.4,<4.0.0)
Requires-Dist: matplotlib (>=3.8.4,<4.0.0)
Requires-Dist: numpy (>=1.26.4,<2.0.0)
Requires-Dist: openpyxl (>=3.1.2,<4.0.0)
Requires-Dist: pandas (>=2.2.2,<3.0.0)
Requires-Dist: pymupdf (>=1.24.1,<2.0.0)
Requires-Dist: rapidfuzz (>=3.8.1,<4.0.0)
Requires-Dist: unidecode (>=1.3.8,<2.0.0)
